[
    {
        "id": 0,
        "titulo": "Evento de integración",
        "cuerpo": "<b> <strong>Evento de Integración Santa Marta 2017. </strong> </b>",
        "galeria": null
    },
    {
        "id": 1,
        "titulo": "Evento de integración",
        "cuerpo": "<b> <strong>Evento de Integración Aratoca 2018. </strong> </b>",
        "galeria": null
    },
    {
        "id": 2,
        "titulo": "Dia del niño ",
        "cuerpo": " <b> Dia de los niños 2018. Es gratificante ser parte del aprendizaje de cnuestros niños.</b>",
        "galeria": null
    },
    {
        "id": 3,
        "titulo": "Talento humano",
        "cuerpo": "<b>  Trabajamos por el bienestar de nuestros trabajadores.  </b>",
        "galeria": null
    },
    {
        "id": 9,
        "titulo": "Celebración Amor y amistad",
        "cuerpo": " <b> La familia transolicar celebra el dia de amor y amistad, mostrando un gran gesto de union y compañerismo.</b>",
        "galeria": null
    },
    {
        "id": 4,
        "titulo": "Evento de Integración",
        "cuerpo": " <b> Evento de integración Aratoca 2018</b>",
        "galeria": null
    },
    {
        "id": 5,
        "titulo": "XIX Congreso Nacional Avicola",
        "cuerpo": " <b> Fenavi septiembre de 2018 - Centro de convenciones CENFER Bucaramanga. </b>",
        "galeria": null
    },
    {
        "id": 7,
        "titulo": "XIX Congreso Nacional Avicola",
        "cuerpo": " <b> Fenavi septiembre de 2018 - Centro de convenciones CENFER Bucaramanga.</b>",
        "galeria": null
    },
    {
        "id": 10,
        "titulo": "Evento conductores Buenaventura",
        "cuerpo": " <b> Evento conductores Buenaventura 2019.</b>",
        "galeria": null
    },
    {
        "id": 6,
        "titulo": "Premiación 2018",
        "cuerpo": " <b> Evento de Premiación mejores conductores 2018, por su fidelidad y compromiso con la empresa.</b>",
        "galeria": null
    },
    {
        "id": 8,
        "titulo": "Mejor Conductor 2018",
        "cuerpo": " <b>Queremos agradecer a nuestros conductores por mantener nuestra compañía en movimiento, siendo el motor que nos impulsa.</b>",
        "galeria": null
    },
    {
        "id": 11,
        "titulo": "Test de Entrada",
        "cuerpo": "Lorem ipsum dolor sit amet, consectetur adipiscing elit. Integer metus sem, mollis id quam sit amet, aliquam ultrices odio. Maecenas eu lobortis libero. Interdum et malesuada fames ac ante ipsum primis in faucibus. Ut ultricies leo eget congue blandit. Ut et sapien venenatis, convallis magna quis, consectetur massa. Vivamus imperdiet mauris a dolor hendrerit, at rutrum augue lobortis. Fusce consectetur erat vitae metus congue blandit. Vivamus in leo quis nulla dapibus dignissim in sit amet erat. Suspendisse pellentesque turpis vel imperdiet viverra. Vestibulum nec nunc commodo, aliquam quam a, malesuada neque. Suspendisse sagittis ex id arcu sagittis gravida. Sed dapibus iaculis metus sed tempus. Vivamus vulputate nisl ac nulla maximus tincidunt. Integer scelerisque justo quis sem consequat tincidunt accumsan a ex.<br>&nbsp;<br>",
        "galeria": [
            {
                "imagen":"servicio1.jpg",
                "pie":"tractomula roja"
            },
            {
                "imagen":"servicio2.jpg",
                "pie":"tractomula blanca"
            },
            {
                "imagen":"servicio3.jpg",
                "pie":null
            }
        ]
    }
]